bedrock_types/__init__.py
bedrock_types/models.py
bedrock_types-0.1.3.dist-info/METADATA
bedrock_types-0.1.3.dist-info/WHEEL
bedrock_types-0.1.3.dist-info/licenses/LICENSE
bedrock_types-0.1.3.dist-info/RECORD
