Metadata-Version: 2.3
Name: bedrock_types
Version: 0.1.3
Summary: Bedrock Converse API Data Types
Project-URL: Homepage, https://github.com/hustshawn/bedrock-types
Project-URL: Issues, https://github.com/hustshawn/bedrock-types/issues
Author-email: Shawn Zhang <hustshawn+pypi@gmail.com>
License-File: LICENSE
Classifier: License :: OSI Approved :: MIT License
Classifier: Operating System :: OS Independent
Classifier: Programming Language :: Python :: 3
Classifier: Programming Language :: Python :: 3 :: Only
Classifier: Programming Language :: Python :: 3.8
Classifier: Programming Language :: Python :: 3.9
Classifier: Programming Language :: Python :: 3.10
Classifier: Programming Language :: Python :: 3.11
Classifier: Programming Language :: Python :: 3.12
Requires-Python: >=3.8
Requires-Dist: pydantic==2.7.3
